varsim/__init__.py
varsim/_core.py
varsim-1.0.8.dist-info/licenses/LICENSE
varsim-1.0.8.dist-info/METADATA
varsim-1.0.8.dist-info/WHEEL
varsim-1.0.8.dist-info/top_level.txt
varsim-1.0.8.dist-info/RECORD
