Metadata-Version: 2.4
Name: varsim
Version: 1.0.8
Summary: Variant Simulator
Author-email: Liu Sun <sunliu@yxnu.edu.cn>, Jian Yang <yangjian@yxnu.edu.cn>
Project-URL: Homepage, https://github.com/liu-sun/VarSim
Project-URL: Issues, https://github.com/liu-sun/VarSim/issues
Classifier: Programming Language :: Python :: 3
Classifier: Operating System :: OS Independent
Classifier: License :: OSI Approved :: MIT License
Requires-Python: >=3.8
License-File: LICENSE
Requires-Dist: biopython
Dynamic: license-file
